rocksdb.libs/libsnappy-637b256b.so.1.1.4
rocksdb.libs/librocksdb-b779d1bb.so.6.7.3
rocksdb.libs/libgflags-d6c9ac2c.so.0.0.0
rocksdb.libs/libbz2-13e8c345.so.1.0.4
rocksdb.libs/liblz4-c29043df.so.1.7.1
rocksdb.libs/libz-eb09ad1d.so.1.2.3
rocksdb-0.7.0.dist-info/top_level.txt
rocksdb-0.7.0.dist-info/METADATA
rocksdb-0.7.0.dist-info/RECORD
rocksdb-0.7.0.dist-info/WHEEL
rocksdb-0.7.0.dist-info/LICENSE.md
rocksdb/interfaces.py
rocksdb/_rocksdb.pyx
rocksdb/comparator.pxd
rocksdb/env.pxd
rocksdb/cache.pxd
rocksdb/status.pxd
rocksdb/merge_operators.py
rocksdb/universal_compaction.pxd
rocksdb/_rocksdb.cpython-37m-x86_64-linux-gnu.so
rocksdb/errors.py
rocksdb/filter_policy.pxd
rocksdb/backup.pxd
rocksdb/logger.pxd
rocksdb/__init__.py
rocksdb/options.pxd
rocksdb/snapshot.pxd
rocksdb/memtablerep.pxd
rocksdb/slice_transform.pxd
rocksdb/table_factory.pxd
rocksdb/slice_.pxd
rocksdb/iterator.pxd
rocksdb/merge_operator.pxd
rocksdb/db.pxd
rocksdb/std_memory.pxd
rocksdb/cpp/memtable_factories.hpp
rocksdb/cpp/write_batch_iter_helper.hpp
rocksdb/cpp/merge_operator_wrapper.hpp
rocksdb/cpp/slice_transform_wrapper.hpp
rocksdb/cpp/comparator_wrapper.hpp
rocksdb/cpp/filter_policy_wrapper.hpp
rocksdb/cpp/utils.hpp
rocksdb/tests/test_memtable.py
rocksdb/tests/test_db.py
rocksdb/tests/__init__.py
rocksdb/tests/test_options.py
