Metadata-Version: 2.1
Name: rocksdb
Version: 0.7.0
Summary: Python bindings for RocksDB
Home-page: https://github.com/twmht/python-rocksdb
Author: Ming Hsuan Tu
Author-email: qrnnis2623891@gmail.com
License: BSD License
Keywords: rocksdb
Platform: UNKNOWN
Requires-Dist: setuptools (>=25)
Provides-Extra: doc
Requires-Dist: sphinx-rtd-theme ; extra == 'doc'
Requires-Dist: sphinx ; extra == 'doc'
Provides-Extra: test
Requires-Dist: pytest ; extra == 'test'
